CHANGES.txt
MANIFEST.in
README.txt
setup.py
CLVault.egg-info/PKG-INFO
CLVault.egg-info/SOURCES.txt
CLVault.egg-info/dependency_links.txt
CLVault.egg-info/entry_points.txt
CLVault.egg-info/requires.txt
CLVault.egg-info/top_level.txt
clvault/__init__.py
clvault/get_password.py
clvault/passwordlist.py
clvault/set_password.py
tests/__init__.py
tests/test_get_password.py