Metadata-Version: 1.0
Name: CLVault
Version: 0.5
Summary: Command-Line utility to store and retrieve passwords
Home-page: http://bitbucket.org/tarek/clvault
Author: Tarek Ziade
Author-email: tarek@ziade.org
License: PSF
Keywords: keyring,password,crypt
Platform: UNKNOWN
